MANIFEST.in
README.rst
setup.py
cmsplugin_googlegroups_widgets/__init__.py
cmsplugin_googlegroups_widgets/admin.py
cmsplugin_googlegroups_widgets/cms_plugins.py
cmsplugin_googlegroups_widgets/models.py
cmsplugin_googlegroups_widgets.egg-info/PKG-INFO
cmsplugin_googlegroups_widgets.egg-info/SOURCES.txt
cmsplugin_googlegroups_widgets.egg-info/dependency_links.txt
cmsplugin_googlegroups_widgets.egg-info/not-zip-safe
cmsplugin_googlegroups_widgets.egg-info/requires.txt
cmsplugin_googlegroups_widgets.egg-info/top_level.txt
cmsplugin_googlegroups_widgets/templates/cmsplugin_googlegroups_widgets/subscribe.html