Metadata-Version: 1.0
Name: cmsplugin-googlegroups-widgets
Version: 0.1
Summary: Google Groups widgets for django-cms 2.2
Home-page: http://bitbucket.org/tonioo/cmsplugin-googlegroups-widgets
Author: Antoine Nguyen
Author-email: tonio@ngyn.org
License: BSD
Keywords: django,django-cms,google groups,widgets
Platform: UNKNOWN
Classifier: Programming Language :: Python
Classifier: Environment :: Web Environment
Classifier: Development Status :: 4 - Beta
Classifier: Intended Audience :: Developers
Classifier: License :: OSI Approved :: BSD License
Classifier: Operating System :: OS Independent
Classifier: Framework :: Django
